google/apps/events_subscriptions/__init__.py
google/apps/events_subscriptions/gapic_version.py
google/apps/events_subscriptions/py.typed
google/apps/events_subscriptions_v1/__init__.py
google/apps/events_subscriptions_v1/gapic_metadata.json
google/apps/events_subscriptions_v1/gapic_version.py
google/apps/events_subscriptions_v1/py.typed
google/apps/events_subscriptions_v1/services/__init__.py
google/apps/events_subscriptions_v1/services/subscriptions_service/__init__.py
google/apps/events_subscriptions_v1/services/subscriptions_service/async_client.py
google/apps/events_subscriptions_v1/services/subscriptions_service/client.py
google/apps/events_subscriptions_v1/services/subscriptions_service/pagers.py
google/apps/events_subscriptions_v1/services/subscriptions_service/transports/__init__.py
google/apps/events_subscriptions_v1/services/subscriptions_service/transports/base.py
google/apps/events_subscriptions_v1/services/subscriptions_service/transports/grpc.py
google/apps/events_subscriptions_v1/services/subscriptions_service/transports/grpc_asyncio.py
google/apps/events_subscriptions_v1/services/subscriptions_service/transports/rest.py
google/apps/events_subscriptions_v1/services/subscriptions_service/transports/rest_base.py
google/apps/events_subscriptions_v1/types/__init__.py
google/apps/events_subscriptions_v1/types/subscription_resource.py
google/apps/events_subscriptions_v1/types/subscriptions_service.py
google/apps/events_subscriptions_v1beta/__init__.py
google/apps/events_subscriptions_v1beta/gapic_metadata.json
google/apps/events_subscriptions_v1beta/gapic_version.py
google/apps/events_subscriptions_v1beta/py.typed
google/apps/events_subscriptions_v1beta/services/__init__.py
google/apps/events_subscriptions_v1beta/services/subscriptions_service/__init__.py
google/apps/events_subscriptions_v1beta/services/subscriptions_service/async_client.py
google/apps/events_subscriptions_v1beta/services/subscriptions_service/client.py
google_apps_events_subscriptions-0.4.0.dist-info/licenses/LICENSE
google_apps_events_subscriptions-0.4.0.dist-info/METADATA
google_apps_events_subscriptions-0.4.0.dist-info/WHEEL
google_apps_events_subscriptions-0.4.0.dist-info/top_level.txt
google_apps_events_subscriptions-0.4.0.dist-info/RECORD
